CHANGELOG
LICENSE
MANIFEST.in
README.rst
setup.cfg
setup.py
gc_recurly.egg-info/PKG-INFO
gc_recurly.egg-info/SOURCES.txt
gc_recurly.egg-info/dependency_links.txt
gc_recurly.egg-info/requires.txt
gc_recurly.egg-info/top_level.txt
gc_recurly.egg-info/zip-safe
recurly/__init__.py
recurly/errors.py
recurly/js.py
recurly/link_header.py
recurly/resource.py
tests/README.md
tests/__init__.py
tests/recurlytests.py
tests/test_js.py
tests/test_recurly.py
tests/test_resources.py
tests/tests_errors.py
tests/fixtures/account/created-with-address.xml
tests/fixtures/account/created.xml
tests/fixtures/account/deleted.xml
tests/fixtures/account/does-not-exist.xml
tests/fixtures/account/exists.xml
tests/fixtures/account/list-active-when-closed.xml
tests/fixtures/account/list-active.xml
tests/fixtures/account/list-closed.xml
tests/fixtures/account/numeric-created.xml
tests/fixtures/account/numeric-deleted.xml
tests/fixtures/account/reopened.xml
tests/fixtures/account/show-taxed.xml
tests/fixtures/account/update-bad-email.xml
tests/fixtures/account/updated.xml
tests/fixtures/account-notes/account1-created.xml
tests/fixtures/account-notes/account1-deleted.xml
tests/fixtures/account-notes/account1-note-list.xml
tests/fixtures/account-notes/account2-created.xml
tests/fixtures/account-notes/account2-deleted.xml
tests/fixtures/account-notes/account2-note-list.xml
tests/fixtures/add-on/created.xml
tests/fixtures/add-on/deleted.xml
tests/fixtures/add-on/exists.xml
tests/fixtures/add-on/need-amount.xml
tests/fixtures/add-on/plan-created.xml
tests/fixtures/add-on/plan-deleted.xml
tests/fixtures/adjustment/account-created.xml
tests/fixtures/adjustment/account-deleted.xml
tests/fixtures/adjustment/account-has-adjustments.xml
tests/fixtures/adjustment/account-has-charges.xml
tests/fixtures/adjustment/account-has-no-charges.xml
tests/fixtures/adjustment/account-has-no-credits.xml
tests/fixtures/adjustment/charged.xml
tests/fixtures/adjustment/original-adjustment-lookup.xml
tests/fixtures/adjustment/original-adjustment-uuid.xml
tests/fixtures/adjustment/original-adjustment.xml
tests/fixtures/adjustment/show-taxed.xml
tests/fixtures/authentication/unauthenticated.xml
tests/fixtures/billing-info/account-created.xml
tests/fixtures/billing-info/account-deleted.xml
tests/fixtures/billing-info/account-embed-created.xml
tests/fixtures/billing-info/account-embed-deleted.xml
tests/fixtures/billing-info/account-embed-exists.xml
tests/fixtures/billing-info/account-embed-token.xml
tests/fixtures/billing-info/account-exists.xml
tests/fixtures/billing-info/created.xml
tests/fixtures/billing-info/deleted.xml
tests/fixtures/billing-info/embedded-exists.xml
tests/fixtures/billing-info/exists.xml
