Metadata-Version: 1.1
Name: gc-recurly
Version: 2.2.19
Summary: The official Recurly API client
Home-page: https://recurly.readme.io/v2.0/page/python
Author: Recurly
Author-email: support@recurly.com
License: MIT
Platform: UNKNOWN
Classifier: Development Status :: 5 - Production/Stable
Classifier: Environment :: Web Environment
Classifier: Intended Audience :: Developers
Classifier: License :: OSI Approved :: MIT License
Classifier: Programming Language :: Python
Classifier: Programming Language :: Python :: 3
Classifier: Topic :: Internet :: WWW/HTTP
